[
  {
    "0": {
      "name": "AI Outreach Automation",
      "value_props": [
        "24/7 outreach",
        "6x more meetings",
        "Automated lead nurturing"
      ],
      "ideal_use_cases": [
        "B2B SaaS mid-market",
        "Growth teams looking to scale outbound"
      ]
    },
    "1": {
      "name": "AI Sales Assistant",
      "value_props": [
        "Automate client follow-ups",
        "Increase response rates by 40%",
        "Save 10+ hours weekly"
      ],
      "ideal_use_cases": [
        "Marketing agencies",
        "Lead generation companies",
        "B2B service providers"
      ]
    },
    "2": {
      "name": "AI Lead Nurturing Engine",
      "value_props": [
        "Personalized outreach sequences",
        "Engage cold leads automatically",
        "Improve pipeline health"
      ],
      "ideal_use_cases": [
        "Enterprise sales teams",
        "CRM-driven businesses"
      ]
    },
    "3": {
      "name": "Startup Growth Outreach Bot",
      "value_props": [
        "Generate investor interest",
        "Book demos faster",
        "Run outreach 24/7"
      ],
      "ideal_use_cases": [
        "Early-stage startups",
        "Founders building traction"
      ]
    },
    "4": {
      "name": "Recruitment Outreach AI",
      "value_props": [
        "Automate candidate sourcing",
        "Personalize recruiter outreach",
        "Engage 3x more applicants"
      ],
      "ideal_use_cases": [
        "Recruitment agencies",
        "HR tech platforms",
        "In-house hiring teams"
      ]
    },
    "5": {
      "name": "Customer Re-Engagement AI",
      "value_props": [
        "Win back inactive users",
        "Send personalized reactivation emails",
        "Boost retention by 25%"
      ],
      "ideal_use_cases": [
        "SaaS retention teams",
        "E-commerce brands"
      ]
    },
    "6": {
      "name": "Real Estate Outreach Assistant",
      "value_props": [
        "Automate buyer/seller follow-ups",
        "Manage property leads efficiently",
        "Close deals faster"
      ],
      "ideal_use_cases": [
        "Real estate agents",
        "Property listing platforms"
      ]
    },
    "7": {
      "name": "Event Outreach Automation",
      "value_props": [
        "Automate sponsor and speaker invites",
        "Fill event pipelines quickly",
        "Save 80% manual effort"
      ],
      "ideal_use_cases": [
        "Event organizers",
        "Conference managers"
      ]
    },
    "8": {
      "name": "Software Engineer Outreach AI",
      "value_props": [
        "Automate recruiter follow-ups",
        "Land interviews faster",
        "Personalized portfolio outreach"
      ],
      "ideal_use_cases": [
        "Software engineers",
        "Tech recruiting agencies",
        "Freelance developers"
      ]
    },
    "9": {
      "name": "Agency Client Retention AI",
      "value_props": [
        "Automate client check-ins",
        "Predict churn before it happens",
        "Increase client lifetime value"
      ],
      "ideal_use_cases": [
        "Digital marketing agencies",
        "Creative studios",
        "Consulting firms"
      ]
    },
    "10": {
      "name": "Product Demo Scheduling AI",
      "value_props": [
        "Book demos automatically",
        "Sync with calendars",
        "Reduce no-shows"
      ],
      "ideal_use_cases": [
        "SaaS sales teams",
        "B2B demo-heavy startups"
      ]
    },
    "11": {
      "name": "AI Proposal Writer",
      "value_props": [
        "Generate client proposals instantly",
        "Personalize for each prospect",
        "Save hours of writing time"
      ],
      "ideal_use_cases": [
        "Agencies",
        "Freelancers",
        "B2B service companies"
      ]
    },
    "12": {
      "name": "LinkedIn Outreach Copilot",
      "value_props": [
        "Automate connection requests",
        "Personalize LinkedIn DMs",
        "Grow your professional network"
      ],
      "ideal_use_cases": [
        "Founders",
        "Sales reps",
        "Consultants building authority"
      ]
    },
    "13": {
      "name": "Cold Email Optimization AI",
      "value_props": [
        "Rewrite emails for higher replies",
        "A/B test automatically",
        "Improve conversion rates"
      ],
      "ideal_use_cases": [
        "Outbound teams",
        "Email marketers",
        "Startup founders"
      ]
    },
    "14": {
      "name": "Investor Outreach Automation",
      "value_props": [
        "Identify active investors",
        "Send personalized pitches",
        "Secure faster responses"
      ],
      "ideal_use_cases": [
        "Startup founders",
        "Fundraising consultants"
      ]
    },
    "id": 1
  }
]